elsi_test/index.py
elsi_test/main.py
elsi_test_two-0.1.dist-info/METADATA
elsi_test_two-0.1.dist-info/WHEEL
elsi_test_two-0.1.dist-info/entry_points.txt
elsi_test_two-0.1.dist-info/top_level.txt
elsi_test_two-0.1.dist-info/RECORD
