Metadata-Version: 2.1
Name: elsi-test-two
Version: 0.1
Summary: A command line tool written in Python to help quickly populate json data into Elasticsearch.
Home-page: https://github.com/itsron717/elsi-test-two
Author: Rounak Vyas
Author-email: itsron143@gmail.com
License: MIT
Platform: UNKNOWN
Requires-Dist: Click
Requires-Dist: elasticsearch
